{
  "node": {
    "0001c3c4f542b962214d8612d6ef08a60b27fdc157": {
      "workers": {
        "app/page": {
          "moduleId": 8685,
          "async": false,
          "exportedName": "getCurrentProfileAction",
          "filename": "src/app/auth/actions.ts"
        }
      },
      "exportedName": "getCurrentProfileAction",
      "filename": "src/app/auth/actions.ts"
    },
    "0090db71646b79d0249d4cbb3f7b2fd9aef4a08a31": {
      "workers": {
        "app/page": {
          "moduleId": 8685,
          "async": false,
          "exportedName": "deleteAllNotificationsAction",
          "filename": "src/app/notificaciones/actions.ts"
        }
      },
      "exportedName": "deleteAllNotificationsAction",
      "filename": "src/app/notificaciones/actions.ts"
    },
    "40f7cce949652620ccaf9972a4ad6077a95eae3354": {
      "workers": {
        "app/page": {
          "moduleId": 8685,
          "async": false,
          "exportedName": "deleteNotificationAction",
          "filename": "src/app/notificaciones/actions.ts"
        }
      },
      "exportedName": "deleteNotificationAction",
      "filename": "src/app/notificaciones/actions.ts"
    },
    "00b208efefee590914f1b080643217344504eaa595": {
      "workers": {
        "app/page": {
          "moduleId": 8685,
          "async": false,
          "exportedName": "listNotificationsAction",
          "filename": "src/app/notificaciones/actions.ts"
        }
      },
      "exportedName": "listNotificationsAction",
      "filename": "src/app/notificaciones/actions.ts"
    },
    "000f0770c15afb6b5d07aa81349a10afe34cb8164c": {
      "workers": {
        "app/page": {
          "moduleId": 8685,
          "async": false,
          "exportedName": "markAllNotificationsReadAction",
          "filename": "src/app/notificaciones/actions.ts"
        }
      },
      "exportedName": "markAllNotificationsReadAction",
      "filename": "src/app/notificaciones/actions.ts"
    },
    "4040b50584c929a78a855a82229984eb0bb0034bc9": {
      "workers": {
        "app/page": {
          "moduleId": 8685,
          "async": false,
          "exportedName": "getPromptInteractionStateAction",
          "filename": "src/app/prompts/actions.ts"
        }
      },
      "exportedName": "getPromptInteractionStateAction",
      "filename": "src/app/prompts/actions.ts"
    },
    "404290a3be575ffa11defbfb33579a5fd9a9f7858d": {
      "workers": {
        "app/page": {
          "moduleId": 8685,
          "async": false,
          "exportedName": "togglePromptLikeAction",
          "filename": "src/app/prompts/actions.ts"
        }
      },
      "exportedName": "togglePromptLikeAction",
      "filename": "src/app/prompts/actions.ts"
    }
  },
  "edge": {}
}